README.rst
setup.py
pyhome/__init__.py
pyhome/__main__.py
pyhome/dircontext.py
pyhome/git.py
pyhome/settings.py
pyhome/symlink.py
pyhome.egg-info/PKG-INFO
pyhome.egg-info/SOURCES.txt
pyhome.egg-info/dependency_links.txt
pyhome.egg-info/entry_points.txt
pyhome.egg-info/top_level.txt